{
  "name": "tabs",
  "type": "component",
  "path": "components/tabs/react/tabs.css",
  "content": ".tabs-list {\n    --_padding-block: 0.65em;\n    --_padding-inline: 0.75em;\n    --_form-control-height: round(calc(2 * var(--_padding-block) + 1em * 1.25), 1px);\n    --_tabs-list-padding: 3px;\n\n    display: inline-flex;\n    background-color: var(--color-surface-lowered);\n    padding: var(--_tabs-list-padding);\n    border-radius: var(--radius-lg);\n    min-height: var(--_form-control-height);\n}\n\n.tabs-trigger {\n    display: inline-flex;\n    align-items: center;\n    justify-content: center;\n    text-decoration: none;\n    cursor: pointer;\n    white-space: nowrap;\n    font-size: inherit;\n    padding-block: 0;\n    background-color: var(--color-surface-lowered);\n    border-width: var(--border-width-thin);\n    border-style: var(--border-style);\n    border-color: transparent;\n    border-radius: var(--radius-md);\n    color: var(--color-text-normal);\n    font-weight: var(--font-weight-medium);\n    gap: var(--space-2xs);\n    padding-inline: var(--_padding-inline);\n    transition-property: color, background-color, border-color, box-shadow;\n    transition-timing-function: var(--ease-out);\n    transition-duration: var(--transition-normal);\n    outline-style: none;\n}\n\n.tabs-trigger[data-state=\"active\"] {\n    background-color: var(--color-surface-default);\n    box-shadow: var(--shadow-sm);\n}\n\n.tabs-trigger:focus-visible {\n    box-shadow: 0 0 0 3px color-mix(in oklab, var(--color-neutral-400) 25%, transparent);\n    border-color: var(--color-neutral-400);\n    z-index: var(--z-raised);\n}\n\n.tabs-trigger:disabled {\n    cursor: not-allowed;\n    opacity: 0.5;\n}\n\n.tabs-panel {\n    outline-style: none;\n}\n\n.tabs-panel[data-state=\"inactive\"] {\n    display: none;\n}\n",
  "frameworks": [
    "react"
  ],
  "dependencies": {
    "react": [
      "clsx",
      "@radix-ui/react-tabs"
    ],
    "css-only": []
  },
  "registryDependencies": {
    "react": [],
    "css-only": []
  }
}