{
  "space": {
    "$type": "dimension",
    "0": {
      "$value": { "value": 0, "unit": "rem" },
      "$extensions": {
        "sh.sugarcube": {
          "fluid": {
            "min": { "value": 0, "unit": "rem" },
            "max": { "value": 0, "unit": "rem" }
          }
        }
      }
    },
    "3xs": {
      "$value": { "value": 0.25, "unit": "rem" },
      "$extensions": {
        "sh.sugarcube": {
          "fluid": {
            "min": { "value": 0.25, "unit": "rem" },
            "max": { "value": 0.25, "unit": "rem" }
          }
        }
      }
    },
    "2xs": {
      "$value": { "value": 0.5, "unit": "rem" },
      "$extensions": {
        "sh.sugarcube": {
          "fluid": {
            "min": { "value": 0.4375, "unit": "rem" },
            "max": { "value": 0.5, "unit": "rem" }
          }
        }
      }
    },
    "xs": {
      "$value": { "value": 0.75, "unit": "rem" },
      "$extensions": {
        "sh.sugarcube": {
          "fluid": {
            "min": { "value": 0.6875, "unit": "rem" },
            "max": { "value": 0.75, "unit": "rem" }
          }
        }
      }
    },
    "sm": {
      "$value": { "value": 1, "unit": "rem" },
      "$extensions": {
        "sh.sugarcube": {
          "fluid": {
            "min": { "value": 0.875, "unit": "rem" },
            "max": { "value": 1, "unit": "rem" }
          }
        }
      }
    },
    "md": {
      "$value": { "value": 1.5, "unit": "rem" },
      "$extensions": {
        "sh.sugarcube": {
          "fluid": {
            "min": { "value": 1.3125, "unit": "rem" },
            "max": { "value": 1.5, "unit": "rem" }
          }
        }
      }
    },
    "lg": {
      "$value": { "value": 2, "unit": "rem" },
      "$extensions": {
        "sh.sugarcube": {
          "fluid": {
            "min": { "value": 1.75, "unit": "rem" },
            "max": { "value": 2, "unit": "rem" }
          }
        }
      }
    },
    "xl": {
      "$value": { "value": 3, "unit": "rem" },
      "$extensions": {
        "sh.sugarcube": {
          "fluid": {
            "min": { "value": 2.625, "unit": "rem" },
            "max": { "value": 3, "unit": "rem" }
          }
        }
      }
    },
    "2xl": {
      "$value": { "value": 4, "unit": "rem" },
      "$extensions": {
        "sh.sugarcube": {
          "fluid": {
            "min": { "value": 3.5, "unit": "rem" },
            "max": { "value": 4, "unit": "rem" }
          }
        }
      }
    },
    "3xl": {
      "$value": { "value": 6, "unit": "rem" },
      "$extensions": {
        "sh.sugarcube": {
          "fluid": {
            "min": { "value": 5.25, "unit": "rem" },
            "max": { "value": 6, "unit": "rem" }
          }
        }
      }
    },
    "3xs-2xs": {
      "$value": { "value": 0.5, "unit": "rem" },
      "$extensions": {
        "sh.sugarcube": {
          "fluid": {
            "min": { "value": 0.25, "unit": "rem" },
            "max": { "value": 0.5, "unit": "rem" }
          }
        }
      }
    },
    "2xs-xs": {
      "$value": { "value": 0.75, "unit": "rem" },
      "$extensions": {
        "sh.sugarcube": {
          "fluid": {
            "min": { "value": 0.4375, "unit": "rem" },
            "max": { "value": 0.75, "unit": "rem" }
          }
        }
      }
    },
    "xs-sm": {
      "$value": { "value": 1, "unit": "rem" },
      "$extensions": {
        "sh.sugarcube": {
          "fluid": {
            "min": { "value": 0.6875, "unit": "rem" },
            "max": { "value": 1, "unit": "rem" }
          }
        }
      }
    },
    "sm-md": {
      "$value": { "value": 1.5, "unit": "rem" },
      "$extensions": {
        "sh.sugarcube": {
          "fluid": {
            "min": { "value": 0.875, "unit": "rem" },
            "max": { "value": 1.5, "unit": "rem" }
          }
        }
      }
    },
    "md-lg": {
      "$value": { "value": 2, "unit": "rem" },
      "$extensions": {
        "sh.sugarcube": {
          "fluid": {
            "min": { "value": 1.3125, "unit": "rem" },
            "max": { "value": 2, "unit": "rem" }
          }
        }
      }
    },
    "lg-xl": {
      "$value": { "value": 3, "unit": "rem" },
      "$extensions": {
        "sh.sugarcube": {
          "fluid": {
            "min": { "value": 1.75, "unit": "rem" },
            "max": { "value": 3, "unit": "rem" }
          }
        }
      }
    },
    "xl-2xl": {
      "$value": { "value": 4, "unit": "rem" },
      "$extensions": {
        "sh.sugarcube": {
          "fluid": {
            "min": { "value": 2.625, "unit": "rem" },
            "max": { "value": 4, "unit": "rem" }
          }
        }
      }
    },
    "2xl-3xl": {
      "$value": { "value": 6, "unit": "rem" },
      "$extensions": {
        "sh.sugarcube": {
          "fluid": {
            "min": { "value": 3.5, "unit": "rem" },
            "max": { "value": 6, "unit": "rem" }
          }
        }
      }
    }
  }
}
